kaiju_automator_lib/__init__.py
kaiju_automator_lib/__version__.py
kaiju_automator_lib/automator_help.py
kaiju_automator_lib/client.py
kaiju_automator_lib/log.py
kaiju_automator_lib/retry_with_backoff.py
kaiju_automator_lib-1.10.2.dist-info/METADATA
kaiju_automator_lib-1.10.2.dist-info/WHEEL
kaiju_automator_lib-1.10.2.dist-info/dependency_links.txt
kaiju_automator_lib-1.10.2.dist-info/top_level.txt
kaiju_automator_lib-1.10.2.dist-info/RECORD
