Metadata-Version: 2.1
Name: kaiju-automator-lib
Version: 1.10.2
Summary: kaiju-automator-lib
Home-page: UNKNOWN
Author: Netflix TSC
Author-email: davidb@netflix.com
License: UNKNOWN
Keywords: kaiju_automator_lib
Platform: UNKNOWN
Classifier: Development Status :: 4 - Beta
Classifier: Environment :: Console
Classifier: Operating System :: OS Independent
Classifier: Programming Language :: Python
Classifier: Programming Language :: Python :: 3 :: Only
Classifier: Programming Language :: Python :: 3.7
Classifier: Topic :: Software Development :: Libraries
Classifier: Topic :: Software Development :: Testing
Requires-Python: >=3.7
Requires-Dist: kaiju-mqtt-py
Requires-Dist: requests
Provides-Extra: test
Requires-Dist: tox ; extra == 'test'
